RsCMPX_UwbMeas/RsCMPX_UwbMeas.py
RsCMPX_UwbMeas/__init__.py
RsCMPX_UwbMeas/enums.py
RsCMPX_UwbMeas/repcap.py
RsCMPX_UwbMeas/CustomFiles/__init__.py
RsCMPX_UwbMeas/CustomFiles/events.py
RsCMPX_UwbMeas/CustomFiles/reliability.py
RsCMPX_UwbMeas/CustomFiles/utilities.py
RsCMPX_UwbMeas/Implementations/__init__.py
RsCMPX_UwbMeas/Implementations/Catalog/UwbMeas.py
RsCMPX_UwbMeas/Implementations/Catalog/__init__.py
RsCMPX_UwbMeas/Implementations/Configure/__init__.py
RsCMPX_UwbMeas/Implementations/Configure/UwbMeas/__init__.py
RsCMPX_UwbMeas/Implementations/Configure/UwbMeas/MultiEval/MprFrequency.py
RsCMPX_UwbMeas/Implementations/Configure/UwbMeas/MultiEval/PhrRate.py
RsCMPX_UwbMeas/Implementations/Configure/UwbMeas/MultiEval/PpLength.py
RsCMPX_UwbMeas/Implementations/Configure/UwbMeas/MultiEval/Ppdu.py
RsCMPX_UwbMeas/Implementations/Configure/UwbMeas/MultiEval/PrfMode.py
RsCMPX_UwbMeas/Implementations/Configure/UwbMeas/MultiEval/PsFormat.py
RsCMPX_UwbMeas/Implementations/Configure/UwbMeas/MultiEval/Result.py
RsCMPX_UwbMeas/Implementations/Configure/UwbMeas/MultiEval/Spectrum.py
RsCMPX_UwbMeas/Implementations/Configure/UwbMeas/MultiEval/StSegments.py
RsCMPX_UwbMeas/Implementations/Configure/UwbMeas/MultiEval/StsLength.py
RsCMPX_UwbMeas/Implementations/Configure/UwbMeas/MultiEval/__init__.py
RsCMPX_UwbMeas/Implementations/Configure/UwbMeas/MultiEval/Modulation/__init__.py
RsCMPX_UwbMeas/Implementations/Configure/UwbMeas/MultiEval/Modulation/Limit/CcError.py
RsCMPX_UwbMeas/Implementations/Configure/UwbMeas/MultiEval/Modulation/Limit/Foffset.py
RsCMPX_UwbMeas/Implementations/Configure/UwbMeas/MultiEval/Modulation/Limit/Plevel.py
RsCMPX_UwbMeas/Implementations/Configure/UwbMeas/MultiEval/Modulation/Limit/PmlWidth.py
RsCMPX_UwbMeas/Implementations/Configure/UwbMeas/MultiEval/Modulation/Limit/SlPeak.py
RsCMPX_UwbMeas/Implementations/Configure/UwbMeas/MultiEval/Modulation/Limit/SmAccuracy.py
RsCMPX_UwbMeas/Implementations/Configure/UwbMeas/MultiEval/Modulation/Limit/__init__.py
RsCMPX_UwbMeas-5.0.20.dist-info/METADATA
RsCMPX_UwbMeas-5.0.20.dist-info/WHEEL
RsCMPX_UwbMeas-5.0.20.dist-info/top_level.txt
RsCMPX_UwbMeas-5.0.20.dist-info/RECORD
